xdot/__init__.py
xdot/__main__.py
xdot/dot/__init__.py
xdot/dot/lexer.py
xdot/dot/parser.py
xdot/dot/scanner.py
xdot/ui/__init__.py
xdot/ui/_xdotparser.py
xdot/ui/actions.py
xdot/ui/animation.py
xdot/ui/colors.py
xdot/ui/elements.py
xdot/ui/pen.py
xdot/ui/window.py
vidot_viz-1.0.1.dist-info/METADATA
vidot_viz-1.0.1.dist-info/WHEEL
vidot_viz-1.0.1.dist-info/entry_points.txt
vidot_viz-1.0.1.dist-info/top_level.txt
vidot_viz-1.0.1.dist-info/RECORD
