Metadata-Version: 2.4
Name: vidot-viz
Version: 1.0.1
Summary: Interactive Verilog visualization tool with GTK interface
Home-page: https://github.com/aliqyan-21/vidot
Author: Aliqyan
Author-email: your@email.com
Classifier: Development Status :: 4 - Beta
Classifier: Intended Audience :: Developers
Classifier: License :: OSI Approved :: MIT License
Classifier: Programming Language :: Python :: 3
Classifier: Operating System :: OS Independent
Requires-Python: >=3.6
Requires-Dist: pycairo>=1.23.0
Requires-Dist: PyGObject>=3.42.0
Dynamic: author
Dynamic: author-email
Dynamic: classifier
Dynamic: description-content-type
Dynamic: home-page
Dynamic: requires-dist
Dynamic: requires-python
Dynamic: summary
